bluestacks_fast_screenshot/LICENSE
bluestacks_fast_screenshot/README.MD
bluestacks_fast_screenshot/__init__.py
bluestacks_fast_screenshot/requirements.txt
bluestacks_fast_screenshot/thirdparty.json
bluestacks_fast_screenshot-0.13.dist-info/LICENSE.rst
bluestacks_fast_screenshot-0.13.dist-info/METADATA
bluestacks_fast_screenshot-0.13.dist-info/WHEEL
bluestacks_fast_screenshot-0.13.dist-info/top_level.txt
bluestacks_fast_screenshot-0.13.dist-info/RECORD
