Metadata-Version: 2.1
Name: bluestacks-fast-screenshot
Version: 0.13
Summary: This module takes screenshots of BlueStacks using the win32 API, resizes and crops them to the same size of an ADB screenshot.
Home-page: https://github.com/hansalemaos/bluestacks_fast_screenshot
Author: Johannes Fischer
Author-email: <aulasparticularesdealemaosp@gmail.com>
License: MIT
Keywords: bluestacks,adb,openCV,win32,screenshots,windows,bot,video,streaming
Classifier: Development Status :: 4 - Beta
Classifier: Programming Language :: Python :: 3 :: Only
Classifier: Programming Language :: Python :: 3.9
Classifier: Topic :: Scientific/Engineering :: Visualization
Classifier: Topic :: Software Development :: Libraries :: Python Modules
Classifier: Topic :: Text Editors :: Text Processing
Classifier: Topic :: Text Processing :: General
Classifier: Topic :: Text Processing :: Indexing
Classifier: Topic :: Text Processing :: Filters
Classifier: Topic :: Utilities
License-File: LICENSE.rst
Requires-Dist: a-cv2-easy-resize
Requires-Dist: a-pandas-ex-automate-win32
Requires-Dist: ctypes-screenshots
Requires-Dist: ctypes-window-info
Requires-Dist: opencv-python
Requires-Dist: pandas
